{
  "project_info": {
    "project_number": "922376180390",
    "project_id": "watersort-2620c",
    "storage_bucket": "watersort-2620c.appspot.com"
  },
  "client": [
    {
      "client_info": {
        "mobilesdk_app_id": "1:922376180390:android:586effcef386a6f2e21a67",
        "android_client_info": {
          "package_name": "com.watersortpuzzle.colorsortpuzzle.watercolorsortpuzzle"
        }
      },
      "oauth_client": [
        {
          "client_id": "922376180390-4ts04gm1ffmju6hb6eh371oanan9cl38.apps.googleusercontent.com",
          "client_type": 3
        }
      ],
      "api_key": [
        {
          "current_key": "AIzaSyD-pUz0OzZ3e5G-1vwFDbZ62NBguJpoLJw"
        }
      ],
      "services": {
        "appinvite_service": {
          "other_platform_oauth_client": [
            {
              "client_id": "922376180390-4ts04gm1ffmju6hb6eh371oanan9cl38.apps.googleusercontent.com",
              "client_type": 3
            }
          ]
        }
      }
    }
  ],
  "configuration_version": "1"
}